NEPMetadataMapping
